{
  "santos": [
    {
      "nombre": "Afro",
      "constelacion": "perro",
      "id": 2
    },
    {
      "id": 3,
      "nombre": "Hyoga",
      "constelacion": "Cisne"
    },
    {
      "nombre": "d",
      "constelacion": "d",
      "id": 4
    },
    {
      "nombre": "Daniel Duarte",
      "constelacion": "a",
      "id": 5
    }
  ],
  "dioses": [
    {
      "id": 1,
      "nombre": "Athenea",
      "de": "Tierra"
    },
    {
      "id": 2,
      "nombre": "Poseidon",
      "de": "Mares"
    },
    {
      "id": 3,
      "nombre": "Hades",
      "de": "Inframundo"
    },
    {
      "id": 4,
      "nombre": "Zeus",
      "de": "Cielos"
    }
  ]
}